{"name":"build-javascript","namedChunkGroups":{"polyfill":{"name":"polyfill","assets":[{"name":"webpack-runtime-9e28cdae85bec1daa11e.js","size":5273},{"name":"polyfill-107c184e81d1e051dde0.js","size":85858}],"filteredAssets":0,"assetsSize":91131,"filteredAuxiliaryAssets":2,"auxiliaryAssetsSize":228810},"app":{"name":"app","assets":[{"name":"webpack-runtime-9e28cdae85bec1daa11e.js","size":5273},{"name":"framework-412ef49158f427965a6a.js","size":129771},{"name":"app-dc445886b4798aef979f.js","size":72020}],"filteredAssets":0,"assetsSize":207064,"filteredAuxiliaryAssets":3,"auxiliaryAssetsSize":670904},"component---src-pages-404-js":{"name":"component---src-pages-404-js","assets":[{"name":"styles.2946856999a97d0666e9.css","size":22120},{"name":"commons-4e35640a0b37b6149fdf.js","size":479354},{"name":"db80b507951befab878d85bf25d3bc8f54f25455-4fbc7b32d76fc22db879.js","size":16018},{"name":"component---src-pages-404-js-854ce16c199349f1068c.js","size":480}],"filteredAssets":0,"assetsSize":517972,"filteredAuxiliaryAssets":3,"auxiliaryAssetsSize":1745803},"component---src-pages-index-tsx":{"name":"component---src-pages-index-tsx","assets":[{"name":"styles.2946856999a97d0666e9.css","size":22120},{"name":"commons-4e35640a0b37b6149fdf.js","size":479354},{"name":"component---src-pages-index-tsx-c577d968fcb888742de5.js","size":777}],"filteredAssets":0,"assetsSize":502251,"filteredAuxiliaryAssets":2,"auxiliaryAssetsSize":1679759},"component---src-templates-[locale]-tsx":{"name":"component---src-templates-[locale]-tsx","assets":[{"name":"styles.2946856999a97d0666e9.css","size":22120},{"name":"commons-4e35640a0b37b6149fdf.js","size":479354},{"name":"db80b507951befab878d85bf25d3bc8f54f25455-4fbc7b32d76fc22db879.js","size":16018},{"name":"component---src-templates-[locale]-tsx-d8861f33764801cbf340.js","size":220004}],"filteredAssets":0,"assetsSize":737496,"filteredAuxiliaryAssets":3,"auxiliaryAssetsSize":2709509}},"assetsByChunkName":{"polyfill":["webpack-runtime-9e28cdae85bec1daa11e.js","polyfill-107c184e81d1e051dde0.js"],"app":["webpack-runtime-9e28cdae85bec1daa11e.js","framework-412ef49158f427965a6a.js","app-dc445886b4798aef979f.js"],"component---src-pages-404-js":["styles.2946856999a97d0666e9.css","commons-4e35640a0b37b6149fdf.js","db80b507951befab878d85bf25d3bc8f54f25455-4fbc7b32d76fc22db879.js","component---src-pages-404-js-854ce16c199349f1068c.js"],"component---src-pages-index-tsx":["styles.2946856999a97d0666e9.css","commons-4e35640a0b37b6149fdf.js","component---src-pages-index-tsx-c577d968fcb888742de5.js"],"component---src-templates-[locale]-tsx":["styles.2946856999a97d0666e9.css","commons-4e35640a0b37b6149fdf.js","db80b507951befab878d85bf25d3bc8f54f25455-4fbc7b32d76fc22db879.js","component---src-templates-[locale]-tsx-d8861f33764801cbf340.js"]},"childAssetsByChunkName":{}}